torchfused/Activation.py
torchfused/__init__.py
torchfused/trition/__init__.py
torchfused/trition/dropout.py
torchfused/trition/fused_linear_layer.py
torchfused/trition/k_activations.py
torchfused/trition/k_dropout.py
torchfused/trition/k_fused_matmul_bw.py
torchfused/trition/k_fused_matmul_fw.py
torchfused/trition/k_layer_norm.py
torchfused/trition/k_softmax.py
torchfused/trition/layer_norm.py
torchfused/trition/softmax.py
torchfused/trition/utils.py
torchfused-0.0.3.dist-info/METADATA
torchfused-0.0.3.dist-info/WHEEL
torchfused-0.0.3.dist-info/top_level.txt
torchfused-0.0.3.dist-info/zip-safe
torchfused-0.0.3.dist-info/RECORD
